dolomite_sce/__init__.py
dolomite_sce/read_single_cell_experiment.py
dolomite_sce/save_single_cell_experiment.py
dolomite_sce-0.3.0.dist-info/LICENSE.txt
dolomite_sce-0.3.0.dist-info/METADATA
dolomite_sce-0.3.0.dist-info/WHEEL
dolomite_sce-0.3.0.dist-info/top_level.txt
dolomite_sce-0.3.0.dist-info/RECORD
