Metadata-Version: 2.1
Name: dolomite-sce
Version: 0.3.0
Summary: Save and load single-cell experiments in the dolomite framework!
Home-page: https://github.com/ArtifactDB/dolomite-sce
Author: LTLA
Author-email: infinite.monkeys.with.keyboards@gmail.com
License: MIT
Project-URL: Documentation, https://github.com/ArtifactDB/dolomite-sce
Platform: any
Classifier: Development Status :: 4 - Beta
Classifier: Programming Language :: Python
Requires-Python: >=3.9
License-File: LICENSE.txt
Requires-Dist: importlib-metadata; python_version < "3.8"
Requires-Dist: dolomite-base>=0.4.2
Requires-Dist: dolomite-se>=0.3.0
Requires-Dist: singlecellexperiment>=0.4.5
Provides-Extra: testing
Requires-Dist: setuptools; extra == "testing"
Requires-Dist: pytest; extra == "testing"
Requires-Dist: pytest-cov; extra == "testing"
